{
    "packages": [
        {
            "maintainer": "Valentin Mocanu",
            "websiteURL": "https://ecrida-rexus.github.io/",
            "platforms": [
                {
                    "category": "ecrida",
                    "name": "ECRIDA",
                    "url": "https://github.com/rontav/ecrida-pcb/releases/download/0.0.2/ecrida-0.0.2.zip",
                    "archiveFileName": "ecrida-0.0.2.zip",
                    "checksum": "SHA-256:f6707c4568986e51d93b4d3841cf692c4174d8a9eb384b5eabb13cbd72992fcf",
                    "help": {
                        "online": ""
                    },
                    "version": "0.0.2",
                    "architecture": "avr",
                    "boards": [
                        {
                            "name": "ECRIDA 2560"
                        }
                    ],
                    "toolsDependencies": [],
                    "size": "5460"
                }
            ],
            "tools": [],
            "email": "mrvali97@gmail.com",
            "name": "ecrida"
        }
    ]
}